pytest_doctest_import.py
pytest_doctest_import-0.1.1.dist-info/LICENSE
pytest_doctest_import-0.1.1.dist-info/METADATA
pytest_doctest_import-0.1.1.dist-info/WHEEL
pytest_doctest_import-0.1.1.dist-info/entry_points.txt
pytest_doctest_import-0.1.1.dist-info/top_level.txt
pytest_doctest_import-0.1.1.dist-info/RECORD
