Metadata-Version: 2.1
Name: pytest-doctest-import
Version: 0.1.1
Summary: A simple pytest plugin to import names and add them to the doctest namespace.
Home-page: https://github.com/rossmacarthur/pytest-doctest-import
Author: Ross MacArthur
Author-email: macarthur.ross@gmail.com
Maintainer: Ross MacArthur
Maintainer-email: macarthur.ross@gmail.com
License: MIT
Platform: UNKNOWN
Classifier: Development Status :: 4 - Beta
Classifier: Framework :: Pytest
Classifier: Intended Audience :: Developers
Classifier: Topic :: Software Development :: Testing
Classifier: Programming Language :: Python
Classifier: Programming Language :: Python :: 2
Classifier: Programming Language :: Python :: 2.7
Classifier: Programming Language :: Python :: 3
Classifier: Programming Language :: Python :: 3.4
Classifier: Programming Language :: Python :: 3.5
Classifier: Programming Language :: Python :: 3.6
Classifier: Programming Language :: Python :: 3.7
Classifier: Programming Language :: Python :: Implementation :: CPython
Classifier: Programming Language :: Python :: Implementation :: PyPy
Classifier: Operating System :: OS Independent
Classifier: License :: OSI Approved :: MIT License
Requires-Python: >=2.7, !=3.0.*, !=3.1.*, !=3.2.*, !=3.3.*
Requires-Dist: pytest (>=3.3.0)
Provides-Extra: linting
Requires-Dist: flake8; extra == 'linting'
Requires-Dist: flake8-quotes; extra == 'linting'
Requires-Dist: pep8-naming; extra == 'linting'
Provides-Extra: testing
Requires-Dist: pytest-cov; extra == 'testing'
